lmsresources/__init__.py
lmsresources/databases/__init__.py
lmsresources/databases/databases.py
lmsresources/middlewares/__init__.py
lmsresources/middlewares/middlewares.py
lmsresources/middlewares/middlewares_test.py
lmsresources/services_interfaces/__init__.py
lmsresources/services_interfaces/admin/__init__.py
lmsresources/services_interfaces/admin/taleemabad_admin.py
lmsresources-0.0.6.dist-info/METADATA
lmsresources-0.0.6.dist-info/WHEEL
lmsresources-0.0.6.dist-info/top_level.txt
lmsresources-0.0.6.dist-info/RECORD
