Metadata-Version: 2.1
Name: lmsresources
Version: 0.0.6
Summary: Resource code for LMS.
Home-page: UNKNOWN
License: UNKNOWN
Platform: UNKNOWN
Requires-Dist: django
Requires-Dist: requests
Requires-Dist: pymongo
